del
testrelease
