Metadata-Version: 2.1
Name: testrelease
Version: 3.3
Summary: testrelease
Home-page: UNKNOWN
Author: testrelease
Author-email: 
License: BSD 3-Clause
Keywords: testrelease,bim,testrelease framework
Platform: UNKNOWN
Classifier: Intended Audience :: Developers
Classifier: License :: OSI Approved :: BSD License
Classifier: Natural Language :: English
Classifier: Programming Language :: Python :: 3.6
Classifier: Programming Language :: Python :: 3.7
Requires-Python: >=3.6
